data/__init__.py
data/datasets/__init__.py
data/datasets/genernal.py
data/metrics/__init__.py
data/metrics/genernal_metrics.py
data/processors/__init__.py
data/processors/genernal.py
seq2seq/__init__.py
seq2seq/callbacks.py
seq2seq/distillation.py
seq2seq/finetune.py
seq2seq/initialization_utils.py
seq2seq/run_eval.py
seq2seq/test_seq2seq_examples.py
seq2seq/utils.py
seq2seq/bertabs/__init__.py
seq2seq/bertabs/configuration_bertabs.py
seq2seq/bertabs/convert_bertabs_original_pytorch_checkpoint.py
seq2seq/bertabs/modeling_bertabs.py
seq2seq/bertabs/run_summarization.py
seq2seq/bertabs/test_utils_summarization.py
seq2seq/bertabs/utils_summarization.py
textclassification/__init__.py
textclassification/run_glue.py
textclassification/run_pl_glue.py
textclassification/run_text_classification.py
textclassification/run_tf_glue.py
textclassification/run_xnli.py
textclassification/serve_text_classification.py
yuccnlptools/__init__.py
yuccnlptools/hello.py
yuccnlptools/lightning_base.py
yuccnlptools/test_examples.py
yuccnlptools/xla_spawn.py
yuccnlptools/data/__init__.py
yuccnlptools/data/datasets/__init__.py
yuccnlptools/data/datasets/genernal.py
yuccnlptools/data/metrics/__init__.py
yuccnlptools/data/metrics/genernal_metrics.py
yuccnlptools/data/processors/__init__.py
yuccnlptools/data/processors/genernal.py
yuccnlptools/seq2seq/__init__.py
yuccnlptools/seq2seq/callbacks.py
yuccnlptools/seq2seq/distillation.py
yuccnlptools/seq2seq/finetune.py
yuccnlptools/seq2seq/initialization_utils.py
yuccnlptools/seq2seq/run_eval.py
yuccnlptools/seq2seq/test_seq2seq_examples.py
yuccnlptools/seq2seq/utils.py
yuccnlptools/seq2seq/bertabs/__init__.py
yuccnlptools/seq2seq/bertabs/configuration_bertabs.py
yuccnlptools/seq2seq/bertabs/convert_bertabs_original_pytorch_checkpoint.py
yuccnlptools/seq2seq/bertabs/modeling_bertabs.py
yuccnlptools/seq2seq/bertabs/run_summarization.py
yuccnlptools/seq2seq/bertabs/test_utils_summarization.py
yuccnlptools/seq2seq/bertabs/utils_summarization.py
yuccnlptools-0.0.15.dist-info/METADATA
yuccnlptools-0.0.15.dist-info/WHEEL
yuccnlptools-0.0.15.dist-info/top_level.txt
yuccnlptools-0.0.15.dist-info/RECORD
