Metadata-Version: 2.1
Name: yuccnlptools
Version: 0.0.15
Summary: 基于pytorch & transformers的文本工具，用于分类、生成等的训练，用于线上服务的部署
Home-page: https://github.com/yucc2018/yuccnlptools
Author: Chen-Chen Yu
Author-email: 6506666@gmail.com
License: UNKNOWN
Platform: UNKNOWN
Classifier: Programming Language :: Python :: 3
Classifier: License :: OSI Approved :: MIT License
Classifier: Operating System :: OS Independent
Requires-Python: >=3.5.0
